htc/__init__.py
htc/_cpp.cp311-win_amd64.pyd
htc/cli.py
htc/run_info.py
htc/settings.py
htc/settings_seg.py
htc/cluster/ClusterConnection.py
htc/cluster/RunGenerator.py
htc/cluster/UpdateCluster.py
htc/cluster/__init__.py
htc/cluster/utils.py
htc/cpp/ParallelExecution.h
htc/cpp/__init__.py
htc/cpp/hierarchical_bootstrapping.h
htc/cpp/tensor_mapping.h
htc/data_exploration/__init__.py
htc/data_processing/DatasetIteration.py
htc/data_processing/__init__.py
htc/data_processing/run_l1_normalization.py
htc/data_processing/run_median_spectra.py
htc/data_processing/run_parameter_images.py
htc/data_processing/run_raw16.py
htc/data_processing/run_standardization.py
htc/data_processing/run_superpixel_prediction.py
htc/evaluation/__init__.py
htc/evaluation/analyze_tfevents.py
htc/evaluation/evaluate_images.py
htc/evaluation/evaluate_superpixels.py
htc/evaluation/ranking.py
htc/evaluation/run_compare_runs.py
htc/evaluation/run_ranking_lr.py
htc/evaluation/run_table_generation.py
htc/evaluation/utils.py
htc/evaluation/metrics/BrierScore.py
htc/evaluation/metrics/ECE.py
htc/evaluation/metrics/NSDToleranceEstimation.py
htc/evaluation/metrics/__init__.py
htc/evaluation/metrics/scores.py
htc/evaluation/model_comparison/__init__.py
htc/evaluation/model_comparison/dataset_size.py
htc/evaluation/model_comparison/paper_runs.py
htc/evaluation/model_comparison/run_challengeR_table.py
htc/fonts/__init__.py
htc/fonts/set_font.py
htc/model_processing/ImageConsumer.py
htc/model_processing/Predictor.py
htc/model_processing/Runner.py
htc/model_processing/SinglePredictionTable.py
htc/model_processing/SinglePredictor.py
htc/model_processing/TestEnsemble.py
htc/model_processing/TestLeaveOneOutPredictor.py
htc/model_processing/TestPredictor.py
htc/model_processing/ValidationPredictor.py
htc/model_processing/__init__.py
htc/model_processing/run_image_figures.py
htc/model_processing/run_inference.py
htc/model_processing/run_median_test_table.py
htc/model_processing/run_multiple.py
imsy_htc-0.0.22.dist-info/licenses/LICENSE.md
imsy_htc-0.0.22.dist-info/METADATA
imsy_htc-0.0.22.dist-info/WHEEL
imsy_htc-0.0.22.dist-info/entry_points.txt
imsy_htc-0.0.22.dist-info/top_level.txt
imsy_htc-0.0.22.dist-info/RECORD
