Metadata-Version: 2.4
Name: imsy-htc
Version: 0.0.22
Summary: Framework for automatic classification and segmentation of hyperspectral images.
Home-page: https://github.com/imsy-dkfz/htc
Author: Division of Intelligent Medical Systems, DKFZ
License: MIT
Keywords: surgical data science,open surgery,hyperspectral imaging,organ segmentation,semantic scene segmentation,deep learning
Classifier: Intended Audience :: Developers
Classifier: Intended Audience :: Science/Research
Classifier: Programming Language :: Python :: 3
Classifier: Programming Language :: Python :: 3.11
Classifier: Programming Language :: Python :: 3.12
Classifier: Programming Language :: Python :: 3.13
Classifier: License :: OSI Approved :: MIT License
Classifier: Operating System :: POSIX :: Linux
Classifier: Operating System :: Microsoft :: Windows
Classifier: Operating System :: MacOS
Classifier: Topic :: Scientific/Engineering
Classifier: Topic :: Scientific/Engineering :: Artificial Intelligence
Classifier: Topic :: Scientific/Engineering :: Image Processing
Classifier: Topic :: Software Development
Classifier: Topic :: Software Development :: Libraries
Classifier: Topic :: Software Development :: Libraries :: Python Modules
Requires-Python: >=3.11
License-File: LICENSE.md
Requires-Dist: numpy>=2
Requires-Dist: scipy
Requires-Dist: scikit-learn
Requires-Dist: Pillow
Requires-Dist: pandas
Requires-Dist: pyarrow
Requires-Dist: matplotlib
Requires-Dist: seaborn
Requires-Dist: plotly
Requires-Dist: kaleido<1
Requires-Dist: jupyterlab
Requires-Dist: tensorboard
Requires-Dist: lightning
Requires-Dist: python-dotenv
Requires-Dist: monai!=1.5.0
Requires-Dist: GPUtil
Requires-Dist: psutil
Requires-Dist: segmentation-models-pytorch
Requires-Dist: kornia!=0.7.4
Requires-Dist: rich
Requires-Dist: threadpoolctl
Requires-Dist: commentjson
Requires-Dist: appdirs
Requires-Dist: blosc
Requires-Dist: torch
Requires-Dist: lazy-imports
Provides-Extra: extra
Requires-Dist: pynrrd; extra == "extra"
Requires-Dist: pypdf; extra == "extra"
Requires-Dist: ipywidgets; extra == "extra"
Requires-Dist: deskew; extra == "extra"
Requires-Dist: paramiko; extra == "extra"
Requires-Dist: opencv-python; extra == "extra"
Requires-Dist: umap-learn; extra == "extra"
Requires-Dist: scikit-image; extra == "extra"
Requires-Dist: openpyxl; extra == "extra"
Requires-Dist: statsmodels; extra == "extra"
Requires-Dist: iterative-stratification; extra == "extra"
Requires-Dist: challenger-pydocker; extra == "extra"
Dynamic: author
Dynamic: classifier
Dynamic: description
Dynamic: description-content-type
Dynamic: home-page
Dynamic: keywords
Dynamic: license
Dynamic: license-file
Dynamic: provides-extra
Dynamic: requires-dist
Dynamic: requires-python
Dynamic: summary
